odoo/addons/mail_attach_existing_attachment_account/README.rst
odoo/addons/mail_attach_existing_attachment_account/__init__.py
odoo/addons/mail_attach_existing_attachment_account/__manifest__.py
odoo/addons/mail_attach_existing_attachment_account/i18n/mail_attach_existing_attachment_account.pot
odoo/addons/mail_attach_existing_attachment_account/readme/CONTRIBUTORS.rst
odoo/addons/mail_attach_existing_attachment_account/readme/DESCRIPTION.rst
odoo/addons/mail_attach_existing_attachment_account/static/description/icon.png
odoo/addons/mail_attach_existing_attachment_account/static/description/index.html
odoo/addons/mail_attach_existing_attachment_account/wizard/account_invoice_send_view.xml
odoo12_addon_mail_attach_existing_attachment_account-12.0.1.0.0.99.dev5.dist-info/METADATA
odoo12_addon_mail_attach_existing_attachment_account-12.0.1.0.0.99.dev5.dist-info/WHEEL
odoo12_addon_mail_attach_existing_attachment_account-12.0.1.0.0.99.dev5.dist-info/top_level.txt
odoo12_addon_mail_attach_existing_attachment_account-12.0.1.0.0.99.dev5.dist-info/RECORD
